param_sweeps/__init__.py
param_sweeps/constants.py
param_sweeps/driver.py
param_sweeps/generate.py
param_sweeps/sample_driver.py
param_sweeps-0.2.1.dist-info/LICENSE
param_sweeps-0.2.1.dist-info/METADATA
param_sweeps-0.2.1.dist-info/WHEEL
param_sweeps-0.2.1.dist-info/RECORD
