Metadata-Version: 2.3
Name: param-sweeps
Version: 0.2.1
Summary: Parameter sweeper for ui.json powered applications.
License: MIT
Keywords: geology,geophysics,earth sciences
Author: Mira Geoscience
Author-email: support@mirageoscience.com
Maintainer: Benjamin Kary
Maintainer-email: benjamink@mirageoscience.com
Requires-Python: >=3.10,<4.0
Classifier: Development Status :: 4 - Beta
Classifier: Intended Audience :: Science/Research
Classifier: License :: OSI Approved :: MIT License
Classifier: Natural Language :: English
Classifier: Operating System :: Microsoft :: Windows
Classifier: Operating System :: POSIX
Classifier: Operating System :: Unix
Classifier: Programming Language :: Python
Classifier: Programming Language :: Python :: 3
Classifier: Programming Language :: Python :: 3.10
Classifier: Programming Language :: Python :: 3.11
Classifier: Programming Language :: Python :: 3.12
Classifier: Programming Language :: Python :: 3.13
Classifier: Topic :: Scientific/Engineering
Classifier: Topic :: Scientific/Engineering :: Mathematics
Classifier: Topic :: Scientific/Engineering :: Physics
Requires-Dist: geoh5py (>=0.11.0a3,<0.12.dev)
Requires-Dist: numpy (>=1.26.0,<1.27.0)
Project-URL: Homepage, https://www.mirageoscience.com/mining-industry-software/python-integration/
Project-URL: Repository, https://github.com/MiraGeoscience/param-sweeps
